relationalai/__init__.py
relationalai/compiler.py
relationalai/debugging.py
relationalai/dependencies.py
relationalai/docutils.py
relationalai/dsl.py
relationalai/errors.py
relationalai/metagen.py
relationalai/metamodel.py
relationalai/rel.py
relationalai/rel_emitter.py
relationalai/rel_utils.py
relationalai/analysis/__init__.py
relationalai/analysis/mechanistic.py
relationalai/analysis/whynot.py
relationalai/auth/__init__.py
relationalai/auth/jwt_generator.py
relationalai/auth/oauth_callback_server.py
relationalai/auth/token_handler.py
relationalai/auth/util.py
relationalai/clients/__init__.py
relationalai/clients/client.py
relationalai/clients/config.py
relationalai/clients/direct_access_client.py
relationalai/clients/exec_txn_poller.py
relationalai/clients/hash_util.py
relationalai/clients/local.py
relationalai/clients/profile_polling.py
relationalai/clients/result_helpers.py
relationalai/clients/types.py
relationalai/clients/util.py
relationalai/clients/resources/__init__.py
relationalai/clients/resources/azure/azure.py
relationalai/clients/resources/snowflake/__init__.py
relationalai/clients/resources/snowflake/cache_store.py
relationalai/clients/resources/snowflake/cli_resources.py
relationalai/clients/resources/snowflake/direct_access_resources.py
relationalai/clients/resources/snowflake/engine_service.py
relationalai/clients/resources/snowflake/engine_state_handlers.py
relationalai/clients/resources/snowflake/error_handlers.py
relationalai/clients/resources/snowflake/export_procedure.py.jinja
relationalai/clients/resources/snowflake/resources_factory.py
relationalai/clients/resources/snowflake/snowflake.py
relationalai/clients/resources/snowflake/use_index_poller.py
relationalai/clients/resources/snowflake/use_index_resources.py
relationalai/clients/resources/snowflake/util.py
relationalai/early_access/__init__.py
relationalai/early_access/builder/__init__.py
relationalai/early_access/builder/builder/__init__.py
relationalai-0.13.4.dist-info/METADATA
relationalai-0.13.4.dist-info/WHEEL
relationalai-0.13.4.dist-info/entry_points.txt
relationalai-0.13.4.dist-info/licenses/LICENSE
relationalai-0.13.4.dist-info/RECORD
