Metadata-Version: 2.4
Name: relationalai
Version: 0.13.4
Summary: RelationalAI Library and CLI
Author-email: RelationalAI <support@relational.ai>
License-File: LICENSE
Requires-Python: >=3.10
Requires-Dist: aiohttp
Requires-Dist: click==8.2.1
Requires-Dist: colorama
Requires-Dist: cryptography
Requires-Dist: gravis
Requires-Dist: inquirerpy
Requires-Dist: lqp==0.2.3
Requires-Dist: nicegui==2.16.1
Requires-Dist: numpy<2
Requires-Dist: opentelemetry-api
Requires-Dist: opentelemetry-exporter-otlp-proto-http
Requires-Dist: opentelemetry-sdk
Requires-Dist: packaging
Requires-Dist: pandas
Requires-Dist: pyarrow
Requires-Dist: pyjwt
Requires-Dist: requests
Requires-Dist: rich
Requires-Dist: snowflake-connector-python[secure-local-storage]
Requires-Dist: snowflake-snowpark-python>=1.38.0
Requires-Dist: toml
Requires-Dist: tomlkit
Requires-Dist: typing-extensions
Requires-Dist: wcwidth
Requires-Dist: websockets
Provides-Extra: dev
Requires-Dist: argcomplete; extra == 'dev'
Requires-Dist: build; extra == 'dev'
Requires-Dist: coverage; extra == 'dev'
Requires-Dist: duckdb; extra == 'dev'
Requires-Dist: faker; extra == 'dev'
Requires-Dist: hupper; extra == 'dev'
Requires-Dist: hypothesis; extra == 'dev'
Requires-Dist: jupyter; extra == 'dev'
Requires-Dist: logscope; extra == 'dev'
Requires-Dist: pandas-stubs; extra == 'dev'
Requires-Dist: pexpect; extra == 'dev'
Requires-Dist: pip-tools; extra == 'dev'
Requires-Dist: polars; extra == 'dev'
Requires-Dist: prompt-toolkit; extra == 'dev'
Requires-Dist: pytest; extra == 'dev'
Requires-Dist: pytest-cov; extra == 'dev'
Requires-Dist: pytest-mock; extra == 'dev'
Requires-Dist: pytest-snapshot; extra == 'dev'
Requires-Dist: pytest-timeout; extra == 'dev'
Requires-Dist: ruff; extra == 'dev'
Requires-Dist: scipy; extra == 'dev'
Requires-Dist: sqlite-utils; extra == 'dev'
Requires-Dist: sympy; extra == 'dev'
Requires-Dist: tablescope; extra == 'dev'
Requires-Dist: watchdog; extra == 'dev'
Provides-Extra: ea
Requires-Dist: dataclasses-json; extra == 'ea'
Requires-Dist: owlready2; extra == 'ea'
Requires-Dist: parameterized; extra == 'ea'
Requires-Dist: pysmt; extra == 'ea'
Requires-Dist: simple-ddl-parser; extra == 'ea'
Requires-Dist: xmltodict; extra == 'ea'
Provides-Extra: legacy
Requires-Dist: rai-sdk>=0.7.5; extra == 'legacy'
